matbench_genmetrics/core/__init__.py
matbench_genmetrics/core/metrics.py
matbench_genmetrics/core/utils/featurize.py
matbench_genmetrics/core/utils/match.py
matbench_genmetrics/core/utils/plotting.py
matbench_genmetrics/mp_time_split/__init__.py
matbench_genmetrics/mp_time_split/splitter.py
matbench_genmetrics/mp_time_split/utils/api.py
matbench_genmetrics/mp_time_split/utils/data.py
matbench_genmetrics/mp_time_split/utils/gen.py
matbench_genmetrics/mp_time_split/utils/mp_dummy_time_summary.json
matbench_genmetrics/mp_time_split/utils/mp_dummy_time_summary.json.gz
matbench_genmetrics/mp_time_split/utils/split.py
matbench_genmetrics-0.6.5.dist-info/LICENSE.txt
matbench_genmetrics-0.6.5.dist-info/METADATA
matbench_genmetrics-0.6.5.dist-info/WHEEL
matbench_genmetrics-0.6.5.dist-info/entry_points.txt
matbench_genmetrics-0.6.5.dist-info/top_level.txt
matbench_genmetrics-0.6.5.dist-info/RECORD
