Metadata-Version: 2.1
Name: matbench-genmetrics
Version: 0.6.5
Summary: Generative materials benchmarking metrics, inspired by CDVAE.
Home-page: https://github.com/sparks-baird/matbench-genmetrics/
Author: sgbaird
Author-email: sterling.baird@utah.edu
License: MIT
Project-URL: Documentation, https://matbench-genmetrics.readthedocs.io
Project-URL: Source, https://github.com/sparks-baird/matbench-genmetrics
Project-URL: Changelog, https://matbench-genmetrics.readthedocs.io/latest/changelog.html
Project-URL: Tracker, https://github.com/sparks-baird/matbench-genmetrics/issues
Project-URL: Conda-Forge, https://anaconda.org/conda-forge/matbench-genmetrics
Project-URL: Download, https://pypi.org/project/matbench-genmetrics/#files
Platform: any
Classifier: Development Status :: 4 - Beta
Classifier: Programming Language :: Python
Requires-Python: >=3.8
License-File: LICENSE.txt
Requires-Dist: numpy
Requires-Dist: pandas
Requires-Dist: scipy
Requires-Dist: scikit-learn
Requires-Dist: pymatgen <=2023.12.18
Requires-Dist: pystow
Requires-Dist: element-coder
Requires-Dist: pymatviz
Requires-Dist: matminer
Requires-Dist: pybtex
Requires-Dist: typing-extensions
Requires-Dist: ruamel.yaml <0.18
Provides-Extra: api
Requires-Dist: mp-api ; (python_version >= "3.9") and extra == 'api'
Provides-Extra: dev
Requires-Dist: conda-souschef ; extra == 'dev'
Requires-Dist: grayskull ; extra == 'dev'
Requires-Dist: pydocstyle ; extra == 'dev'
Requires-Dist: mypy ; extra == 'dev'
Requires-Dist: flake8 ; extra == 'dev'
Requires-Dist: black ; extra == 'dev'
Requires-Dist: ipykernel ; extra == 'dev'
Requires-Dist: pre-commit ; extra == 'dev'
Provides-Extra: testing
Requires-Dist: setuptools ; extra == 'testing'
Requires-Dist: pytest ; extra == 'testing'
Requires-Dist: pytest-cov ; extra == 'testing'
Requires-Dist: mp-api ; extra == 'testing'
